__init__.py
test_pypi_security.py
test_pypi_security-0.1.3.dist-info/METADATA
test_pypi_security-0.1.3.dist-info/WHEEL
test_pypi_security-0.1.3.dist-info/top_level.txt
test_pypi_security-0.1.3.dist-info/RECORD
