Metadata-Version: 2.1
Name: test_pypi_security
Version: 0.1.3
Summary: Test of PyPI security
Home-page: https://github.com/ArthurLeFloch/
Author: Arthur Le Floch
Author-email: alf.github@gmail.com
License: UNKNOWN
Platform: UNKNOWN
Classifier: Intended Audience :: Developers
Classifier: Programming Language :: Python :: 3
Classifier: Programming Language :: Python :: 3.7
Classifier: Programming Language :: Python :: 3.8
Classifier: Programming Language :: Python :: 3.9
